{
  "last_updated": "2026-04-30T08:25:11.131104+00:00",
  "studios": [
    {
      "id": "yoga-loft-chur",
      "name": "Yoga Loft Chur",
      "website": "https://www.yogaloftchur.ch/",
      "schedule_url": "https://www.yogaloftchur.ch/kontakt",
      "addresses": [
        {
          "street": "Bahnhofplatz 10",
          "zip": "7001",
          "city": "Chur",
          "label": "Zentrumsnah"
        }
      ],
      "phone": "+41 76 731 58 15",
      "email": "info@yogaloftchur.ch",
      "styles": [
        "Yin Yoga",
        "Vinyasa Flow",
        "Schwangerschaftsyoga"
      ],
      "teachers": [
        "Claudia Cadonau"
      ],
      "description": "Yoga Loft im Zentrum von Chur nahe dem Bahnhof. Abwechslungsreiches Yogaangebot mit wöchentlichen Lektionen, Kursen, Workshops, Schwangerschaftsyoga und Massagen. Birthlight-zertifiziert.",
      "booking_platform": "",
      "drop_in": true,
      "languages": [
        "Deutsch"
      ],
      "special_features": [
        "Schwangerschaftsyoga",
        "Birthlight zertifiziert",
        "Naturheilkunde-Massagen",
        "Workshops"
      ],
      "lat": 46.853,
      "lng": 9.53,
      "active": true,
      "classes": [],
      "scrape_status": "scraped",
      "last_scraped": "2026-04-30T08:23:46.115280+00:00",
      "detected_booking_links": [
        {
          "platform": "mindbody",
          "url": "https://clients.mindbodyonline.com/help?studioid=282894"
        }
      ],
      "pricing": {
        "currency": "CHF",
        "verified": true,
        "source": "https://www.yogaloftchur.ch/preise",
        "last_checked": "2026-04-30T08:23:49.904738+00:00",
        "single": 35.0
      },
      "_meta": {
        "last_scraped": "2026-04-30T08:23:49.904799+00:00",
        "last_price_check": "2026-04-30T08:23:49.904799+00:00",
        "scrape_status": "scraped",
        "booking_links": [
          {
            "platform": "mindbody",
            "url": "https://clients.mindbodyonline.com/help?studioid=282894"
          }
        ],
        "source_urls": {
          "website": "https://www.yogaloftchur.ch/",
          "schedule": "https://www.yogaloftchur.ch/kontakt",
          "pricing": "https://www.yogaloftchur.ch/preise"
        }
      }
    },
    {
      "id": "yoga-pyramide-chur",
      "name": "Yoga Pyramide",
      "website": "https://yogapyramide.ch/",
      "schedule_url": "",
      "addresses": [
        {
          "street": "Rabengasse 10",
          "zip": "7000",
          "city": "Chur",
          "label": "Altstadt"
        }
      ],
      "phone": "+41 81 641 36 41",
      "email": "info@yogapyramide.ch",
      "styles": [
        "Yoga"
      ],
      "teachers": [
        "Beatrice Loringett"
      ],
      "description": "Yoga Pyramide mitten in der Altstadt von Chur - ein Ort der Ruhe und Stille. Workshops und regelmässige Kurse.",
      "booking_platform": "",
      "drop_in": true,
      "languages": [
        "Deutsch"
      ],
      "special_features": [
        "Workshops",
        "Altstadt-Lage"
      ],
      "lat": 46.8498,
      "lng": 9.531,
      "active": true,
      "classes": [],
      "pricing": {
        "single": 35,
        "card_10": 270,
        "trial": 22,
        "currency": "CHF",
        "verified": true,
        "source": "https://yogapyramide.ch/preise",
        "last_checked": "2026-04-30T08:24:03.874713+00:00"
      },
      "scrape_status": "scraped",
      "last_scraped": "2026-04-30T08:23:51.334507+00:00",
      "_meta": {
        "last_scraped": "2026-04-30T08:24:03.874733+00:00",
        "last_price_check": null,
        "scrape_status": "scraped",
        "booking_links": [],
        "source_urls": {
          "website": "https://yogapyramide.ch/"
        }
      }
    },
    {
      "id": "belude-yoga-chur",
      "name": "Belude - Yoga & Klang",
      "website": "https://belude.ch/",
      "schedule_url": "",
      "addresses": [
        {
          "street": "Reichsgasse 25",
          "zip": "7000",
          "city": "Chur",
          "label": ""
        }
      ],
      "phone": "+41 77 406 52 30",
      "email": "lucrezia@belude.ch",
      "styles": [
        "Yoga",
        "Yoga & Klang",
        "Aerial Yoga",
        "Taichi",
        "Qigong"
      ],
      "teachers": [
        "Lucrezia Decurtins"
      ],
      "description": "Fortlaufende Kurse in Yoga, Yoga & Klang, Klangreisen und klangvollem Zentrieren in Chur. Auch Seminarraum-Vermietung.",
      "booking_platform": "",
      "drop_in": true,
      "languages": [
        "Deutsch"
      ],
      "special_features": [
        "Klangarbeit",
        "Klangreisen",
        "Aerial Yoga",
        "Seminarraumvermietung"
      ],
      "lat": 46.851,
      "lng": 9.5295,
      "active": true,
      "classes": [],
      "pricing": {
        "single": 27,
        "currency": "CHF",
        "verified": true,
        "source": "https://belude.ch/programm.html",
        "last_checked": "2026-04-30T08:24:10.762064+00:00"
      },
      "scrape_status": "scraped",
      "last_scraped": "2026-04-30T08:24:04.592493+00:00",
      "_meta": {
        "last_scraped": "2026-04-30T08:24:10.762085+00:00",
        "last_price_check": null,
        "scrape_status": "scraped",
        "booking_links": [],
        "source_urls": {
          "website": "https://belude.ch/"
        }
      }
    },
    {
      "id": "raw-yoga-chur",
      "name": "RAW Yoga",
      "website": "https://rawstation.ch/yoga-by-raw-station/",
      "schedule_url": "https://www.eversports.ch/s/raw-yoga",
      "addresses": [
        {
          "street": "Bankstrasse 8",
          "zip": "7000",
          "city": "Chur",
          "label": "RAW Station"
        }
      ],
      "phone": "",
      "email": "",
      "styles": [
        "Yoga"
      ],
      "teachers": [
        "Gila Capol"
      ],
      "description": "RAW Yoga im Herzen der Altstadt Chur, im neuen urbanen Treffpunkt RAW Station. Tägliche Yoga-Angebote in einer Oase für Gemeinschaft und achtsame Begegnung. Kein Abo oder Voranmeldung nötig für die erste Klasse.",
      "booking_platform": "Eversports",
      "drop_in": true,
      "languages": [
        "Deutsch"
      ],
      "special_features": [
        "Drop-in ohne Anmeldung",
        "Spontan buchbar",
        "Urban Community Space"
      ],
      "lat": 46.85,
      "lng": 9.5285,
      "active": true,
      "classes": [],
      "scrape_status": "no_data",
      "_meta": {
        "last_scraped": "2026-04-30T08:24:49.348264+00:00",
        "last_price_check": null,
        "scrape_status": "no_data",
        "booking_links": [
          {
            "platform": "eversports",
            "url": "https://www.eversports.ch/s/_b2_iQ"
          },
          {
            "platform": "eversports",
            "url": "https://www.eversports.ch/s/_b2_iQ"
          },
          {
            "platform": "eversports",
            "url": "https://www.eversports.ch/s/_b2_iQ"
          },
          {
            "platform": "eversports",
            "url": "https://www.eversports.ch/s/_b2_iQ"
          },
          {
            "platform": "eversports",
            "url": "https://www.eversports.ch/s/_b2_iQ"
          },
          {
            "platform": "eversports",
            "url": "https://www.eversports.ch/s/_b2_iQ"
          },
          {
            "platform": "eversports",
            "url": "https://www.eversports.ch/s/_b2_iQ"
          },
          {
            "platform": "eversports",
            "url": "https://www.eversports.ch/s/_b2_iQ"
          },
          {
            "platform": "eversports",
            "url": "https://www.eversports.ch/s/_b2_iQ"
          },
          {
            "platform": "eversports",
            "url": "https://www.eversports.ch/s/_b2_iQ"
          }
        ],
        "source_urls": {
          "website": "https://rawstation.ch/yoga-by-raw-station/",
          "schedule": "https://www.eversports.ch/s/raw-yoga"
        }
      }
    },
    {
      "id": "flux2motus-davos",
      "name": "flux2motus - Yoga & Massage",
      "website": "https://www.flux2motus.ch/",
      "schedule_url": "",
      "addresses": [
        {
          "street": "Mattastrasse 6",
          "zip": "7270",
          "city": "Davos Platz",
          "label": ""
        }
      ],
      "phone": "",
      "email": "",
      "styles": [
        "Yoga"
      ],
      "teachers": [
        "Tajana Adank"
      ],
      "description": "Yoga und Massage in Davos, Arosa und Chur. Geführt von Tajana Adank, bietet Yoga-Kurse und Massagen in der Region Graubünden.",
      "booking_platform": "",
      "drop_in": true,
      "languages": [
        "Deutsch"
      ],
      "special_features": [
        "Massage",
        "Mehrere Standorte in Graubünden"
      ],
      "lat": 46.793,
      "lng": 9.835,
      "active": false,
      "closed_note": "Website nicht mehr erreichbar",
      "classes": []
    },
    {
      "id": "davos-yoga",
      "name": "Davos Yoga",
      "website": "https://davosyoga.ch/",
      "schedule_url": "",
      "addresses": [
        {
          "street": "",
          "zip": "7270",
          "city": "Davos Platz",
          "label": ""
        }
      ],
      "phone": "",
      "email": "",
      "styles": [
        "Yoga"
      ],
      "teachers": [],
      "description": "Yoga-Oase in Davos Platz. Yoga-Klassen für Anfänger und Fortgeschrittene in Davos.",
      "booking_platform": "",
      "drop_in": true,
      "languages": [
        "Deutsch"
      ],
      "special_features": [],
      "lat": 46.7935,
      "lng": 9.836,
      "active": false,
      "closed_note": "Website nicht mehr erreichbar",
      "classes": []
    },
    {
      "id": "yogaplaza-davos",
      "name": "Yogaplaza Davos",
      "website": "https://www.yogaplazadavos.ch/",
      "schedule_url": "https://www.eversports.ch/s/yogaplaza-davos",
      "addresses": [
        {
          "street": "Mattastrasse 6",
          "zip": "7270",
          "city": "Davos Platz",
          "label": ""
        }
      ],
      "phone": "+41 81 415 21 88",
      "email": "",
      "styles": [
        "Yoga"
      ],
      "teachers": [],
      "description": "Yogaplaza in Davos Platz bietet Klassen für Einsteiger und Erfahrene. Es gibt eine passende Klasse für jeden. Erreichbar auch via WhatsApp.",
      "booking_platform": "Eversports",
      "drop_in": true,
      "languages": [
        "Deutsch"
      ],
      "special_features": [
        "WhatsApp Kontakt"
      ],
      "lat": 46.793,
      "lng": 9.835,
      "active": true,
      "classes": [],
      "scrape_status": "scraped",
      "_meta": {
        "last_scraped": "2026-04-30T08:24:56.311999+00:00",
        "last_price_check": null,
        "scrape_status": "scraped",
        "booking_links": [
          {
            "platform": "eversports",
            "url": "https://www.eversportscorporate.com/corporate-sports/"
          },
          {
            "platform": "eversports",
            "url": "https://www.eversportscorporate.com/corporate-sports/"
          },
          {
            "platform": "eversports",
            "url": "https://www.eversportsmanager.com/de/partner-werden/?utm_source=Referrals&utm_medium=marketplace-for-studios&utm_campaign=mp-b2b-landingpage"
          },
          {
            "platform": "eversports",
            "url": "https://www.eversportsmanager.com/de/uber-uns/"
          },
          {
            "platform": "eversports",
            "url": "https://blog.eversports.com/?utm_source=marketplace&utm_medium=footer_link&utm_campaign=b2c_blog_footer_link"
          },
          {
            "platform": "eversports",
            "url": "https://www.eversportsmanager.com/de/uber-uns/#jobs"
          },
          {
            "platform": "eversports",
            "url": "https://www.eversportscorporate.com/"
          },
          {
            "platform": "eversports",
            "url": "https://www.eversportsmanager.com/de/partner-werden/?utm_source=Referrals&utm_medium=marketplace-website-footer&utm_campaign=mp-b2b-landingpage"
          },
          {
            "platform": "eversports",
            "url": "https://www.eversportsmanager.com/de/preise/?utm_source=Referrals&utm_medium=marketplace-pricing-footer&utm_campaign=mp-b2b-pricingpage"
          },
          {
            "platform": "eversports",
            "url": "https://www.eversportsmanager.com/de/demo/?utm_source=Referrals&utm_medium=marketplace-demo-footer&utm_campaign=mp-b2b-demopage"
          },
          {
            "platform": "eversports",
            "url": "https://www.facebook.com/eversports"
          },
          {
            "platform": "eversports",
            "url": "https://www.instagram.com/eversports_official/"
          }
        ],
        "source_urls": {
          "website": "https://www.yogaplazadavos.ch/",
          "schedule": "https://www.eversports.ch/s/yogaplaza-davos"
        }
      },
      "last_scraped": "2026-04-30T08:24:49.710778+00:00",
      "detected_booking_links": [
        {
          "platform": "eversports",
          "url": "https://www.eversportscorporate.com/corporate-sports/"
        },
        {
          "platform": "eversports",
          "url": "https://www.eversportscorporate.com/corporate-sports/"
        },
        {
          "platform": "eversports",
          "url": "https://www.eversportsmanager.com/de/partner-werden/?utm_source=Referrals&utm_medium=marketplace-for-studios&utm_campaign=mp-b2b-landingpage"
        },
        {
          "platform": "eversports",
          "url": "https://www.eversportsmanager.com/de/uber-uns/"
        },
        {
          "platform": "eversports",
          "url": "https://blog.eversports.com/?utm_source=marketplace&utm_medium=footer_link&utm_campaign=b2c_blog_footer_link"
        },
        {
          "platform": "eversports",
          "url": "https://www.eversportsmanager.com/de/uber-uns/#jobs"
        },
        {
          "platform": "eversports",
          "url": "https://www.eversportscorporate.com/"
        },
        {
          "platform": "eversports",
          "url": "https://www.eversportsmanager.com/de/partner-werden/?utm_source=Referrals&utm_medium=marketplace-website-footer&utm_campaign=mp-b2b-landingpage"
        },
        {
          "platform": "eversports",
          "url": "https://www.eversportsmanager.com/de/preise/?utm_source=Referrals&utm_medium=marketplace-pricing-footer&utm_campaign=mp-b2b-pricingpage"
        },
        {
          "platform": "eversports",
          "url": "https://www.eversportsmanager.com/de/demo/?utm_source=Referrals&utm_medium=marketplace-demo-footer&utm_campaign=mp-b2b-demopage"
        },
        {
          "platform": "eversports",
          "url": "https://www.facebook.com/eversports"
        },
        {
          "platform": "eversports",
          "url": "https://www.instagram.com/eversports_official/"
        }
      ]
    },
    {
      "id": "yoga-loft-engadin-samedan",
      "name": "Yoga Loft Engadin",
      "website": "https://yogaloftengadin.ch/",
      "schedule_url": "",
      "addresses": [
        {
          "street": "Cho d'Punt 10",
          "zip": "7503",
          "city": "Samedan",
          "label": ""
        }
      ],
      "phone": "+41 76 501 43 42",
      "email": "sol@yogastrologa.com",
      "styles": [
        "Ashtanga Yoga",
        "Hatha Yoga",
        "Vinyasa"
      ],
      "teachers": [],
      "description": "Holistisches Yoga-Studio in Samedan im Engadin. Bietet fachkundigen Yogaunterricht in Ashtanga, Hatha und Vinyasa sowie Astrologie-Sessions, Reiki, Tarot und Sound Baths.",
      "booking_platform": "",
      "drop_in": true,
      "languages": [
        "Deutsch",
        "English"
      ],
      "special_features": [
        "Sound Baths",
        "Reiki",
        "Astrologie",
        "Tarot"
      ],
      "lat": 46.533,
      "lng": 9.872,
      "active": true,
      "classes": [],
      "scrape_status": "no_data",
      "last_scraped": "2026-04-27T08:35:20.376335+00:00",
      "_meta": {
        "last_scraped": "2026-04-30T08:25:00.140301+00:00",
        "last_price_check": "2026-03-26T22:22:14.808879+00:00",
        "scrape_status": "scraped",
        "booking_links": [],
        "source_urls": {
          "website": "https://yogaloftengadin.ch/",
          "pricing": "https://yogaloftengadin.ch/prices/"
        }
      },
      "pricing": {
        "single": 35,
        "card_10": 333,
        "currency": "CHF",
        "verified": true,
        "source": "https://yogaloftengadin.ch/prices/",
        "last_checked": "2026-04-30T08:25:00.140284+00:00"
      }
    },
    {
      "id": "acroyoga-group-chur",
      "name": "Acroyoga Group Graubünden",
      "website": "https://acroyoga.group/",
      "schedule_url": "",
      "addresses": [
        {
          "street": "Masanserstrasse 223",
          "zip": "7000",
          "city": "Chur",
          "label": "Turnhalle Masans (Montag)"
        }
      ],
      "phone": "",
      "email": "info@acroyoga.group",
      "styles": [
        "Acroyoga",
        "Partnerakrobatik",
        "Luftakrobatik"
      ],
      "teachers": [],
      "description": "Acroyoga und Partnerakrobatik in Chur und Samedan. Montags in der Turnhalle Masans und Donnerstags in der Turnhalle Montalin 2. Im Sommer auch draussen. Auch Sessions in Samedan (Montags 19:30).",
      "booking_platform": "",
      "drop_in": true,
      "languages": [
        "Deutsch"
      ],
      "special_features": [
        "Acroyoga",
        "Partnerakrobatik",
        "Outdoor Training im Sommer"
      ],
      "lat": 46.855,
      "lng": 9.538,
      "active": true,
      "classes": [],
      "pricing": {
        "single": 5,
        "currency": "CHF",
        "verified": true,
        "source": "https://acroyoga.group/",
        "last_checked": "2026-04-30T08:25:11.131080+00:00"
      },
      "scrape_status": "scraped",
      "last_scraped": "2026-04-30T08:25:00.914403+00:00",
      "_meta": {
        "last_scraped": "2026-04-30T08:25:11.131095+00:00",
        "last_price_check": "2026-03-26T21:37:22.955099+00:00",
        "scrape_status": "scraped",
        "booking_links": [],
        "source_urls": {
          "website": "https://acroyoga.group/",
          "pricing": "https://acroyoga.group/"
        }
      }
    }
  ]
}
